<?xml version="1.0" encoding="UTF-8"?>
<flights xmlns:xsd="http://www.w3.org/2001/XMLSchema"
         xmlns="http://www.finavia.fi/FlightsService.xsd">
   <arr>
      <header>
         <timestamp>2022-12-17T13:12:09Z</timestamp>
         <from>Finavia</from>
         <description>Arrival flight data</description>
      </header>
      <body>
         <flight>
            <h_apt>RVN</h_apt>
            <fltnr>LAV5245</fltnr>
            <sdt>2022-12-17T11:30:00Z</sdt>
            <sdate>20221217</sdate>
            <acreg>ECNGC</acreg>
            <actype>B738</actype>
            <mfltnr/>
            <cflight_1>AP5245</cflight_1>
            <cflight_2/>
            <cflight_3/>
            <cflight_4/>
            <cflight_5/>
            <cflight_6/>
            <route_1>DUB</route_1>
            <route_2/>
            <route_3/>
            <route_4/>
            <route_n_1>Dublin</route_n_1>
            <route_n_2/>
            <route_n_3/>
            <route_n_4/>
            <park/>
            <park_prv/>
            <gate/>
            <gate_prv/>
            <prm>A</prm>
            <prt>Landed</prt>
            <prt_f>Laskeutunut</prt_f>
            <prt_s>Landat</prt_s>
            <est_d>2022-12-17T12:06:00Z</est_d>
            <pest_d>2022-12-17T12:06:00Z</pest_d>
            <act_d>2022-12-17T12:06:00Z</act_d>
            <ablk_d/>
            <bltarea/>
            <callsign>LAV5245</callsign>
         </flight>
      </body>
   </arr>
</flights>